odoo/addons/l10n_br_coa_generic/README.rst
odoo/addons/l10n_br_coa_generic/__init__.py
odoo/addons/l10n_br_coa_generic/__manifest__.py
odoo/addons/l10n_br_coa_generic/hooks.py
odoo/addons/l10n_br_coa_generic/data/account.account.template.csv
odoo/addons/l10n_br_coa_generic/data/account_fiscal_position_template.xml
odoo/addons/l10n_br_coa_generic/data/account_group.xml
odoo/addons/l10n_br_coa_generic/data/l10n_br_coa.account.tax.group.account.template.csv
odoo/addons/l10n_br_coa_generic/data/l10n_br_coa_generic_template.xml
odoo/addons/l10n_br_coa_generic/data/l10n_br_coa_generic_template_post.xml
odoo/addons/l10n_br_coa_generic/demo/account_journal.xml
odoo/addons/l10n_br_coa_generic/i18n/l10n_br_coa_generic.pot
odoo/addons/l10n_br_coa_generic/i18n/pt_BR.po
odoo/addons/l10n_br_coa_generic/readme/CONFIGURE.rst
odoo/addons/l10n_br_coa_generic/readme/CONTRIBUTORS.rst
odoo/addons/l10n_br_coa_generic/readme/DESCRIPTION.rst
odoo/addons/l10n_br_coa_generic/readme/INSTALL.rst
odoo/addons/l10n_br_coa_generic/readme/ROADMAP.rst
odoo/addons/l10n_br_coa_generic/readme/USAGE.rst
odoo/addons/l10n_br_coa_generic/static/description/icon.png
odoo/addons/l10n_br_coa_generic/static/description/index.html
odoo/addons/l10n_br_coa_generic/static/pdf/Livro_Escrituracao_contabil.pdf
odoo/addons/l10n_br_coa_generic/tests/__init__.py
odoo/addons/l10n_br_coa_generic/tests/test_l10n_br_coa_generic.py
odoo13_addon_l10n_br_coa_generic-13.0.2.0.0.dist-info/METADATA
odoo13_addon_l10n_br_coa_generic-13.0.2.0.0.dist-info/WHEEL
odoo13_addon_l10n_br_coa_generic-13.0.2.0.0.dist-info/top_level.txt
odoo13_addon_l10n_br_coa_generic-13.0.2.0.0.dist-info/RECORD
