Metadata-Version: 2.1
Name: odoo13-addon-l10n-br-coa-generic
Version: 13.0.2.0.0
Summary: Plano de Contas para empresas do Regime normal (Micro e pequenas empresas)
Home-page: https://github.com/OCA/l10n-brazil
Author: KMEE, Odoo Community Association (OCA)
Author-email: support@odoo-community.org
License: AGPL-3
Platform: UNKNOWN
Classifier: Programming Language :: Python
Classifier: Framework :: Odoo
Classifier: License :: OSI Approved :: GNU Affero General Public License v3
Classifier: Development Status :: 5 - Production/Stable
Requires-Python: >=3.5
Requires-Dist: odoo13-addon-l10n-br-coa
Requires-Dist: odoo (<13.1dev,>=13.0a)
